lexy_py/__init__.py
lexy_py/binding/__init__.py
lexy_py/binding/client.py
lexy_py/binding/models.py
lexy_py/client.py
lexy_py/collection/__init__.py
lexy_py/collection/client.py
lexy_py/collection/models.py
lexy_py/document/__init__.py
lexy_py/document/client.py
lexy_py/document/models.py
lexy_py/exceptions.py
lexy_py/filters.py
lexy_py/index/__init__.py
lexy_py/index/client.py
lexy_py/index/models.py
lexy_py/settings.py
lexy_py/storage.py
lexy_py/transformer/__init__.py
lexy_py/transformer/client.py
lexy_py/transformer/models.py
lexy_py-0.0.3.dist-info/METADATA
lexy_py-0.0.3.dist-info/WHEEL
lexy_py-0.0.3.dist-info/RECORD
